bwt_api/__init__.py
bwt_api/api.py
bwt_api/bwt.py
bwt_api/data.py
bwt_api/error.py
bwt_api/exception.py
bwt_api/skeleton.py
bwt_api-0.6.1.dist-info/licenses/LICENSE.txt
bwt_api-0.6.1.dist-info/METADATA
bwt_api-0.6.1.dist-info/WHEEL
bwt_api-0.6.1.dist-info/entry_points.txt
bwt_api-0.6.1.dist-info/top_level.txt
bwt_api-0.6.1.dist-info/RECORD
