Metadata-Version: 2.4
Name: bwt_api
Version: 0.6.1
Summary: Python API to access the local BWT Perla API.
Home-page: https://github.com/dkarv/bwt_api
Author: dkarv
Author-email: punzet.david@gmail.com
License: MIT
Project-URL: Documentation, https://github.com/dkarv/bwt_api/blob/main/README.rst
Project-URL: Source, https://github.com/dkarv/bwt_api
Project-URL: Changelog, https://github.com/dkarv/bwt_api/blob/main/CHANGELOG.rst
Project-URL: Tracker, https://github.com/dkarv/bwt_api/issues
Platform: any
Classifier: Development Status :: 4 - Beta
Classifier: Programming Language :: Python
Requires-Python: >=3.10
License-File: LICENSE.txt
Requires-Dist: aiohttp
Provides-Extra: testing
Requires-Dist: flake8; extra == "testing"
Requires-Dist: setuptools; extra == "testing"
Requires-Dist: pytest; extra == "testing"
Requires-Dist: pytest-cov; extra == "testing"
Requires-Dist: pytest-asyncio; extra == "testing"
Requires-Dist: aioresponses; extra == "testing"
Dynamic: license-file
